dttb/__init__.py
dttb/py.typed
dttb-0.2.1.dist-info/licenses/LICENSE
dttb-0.2.1.dist-info/WHEEL
dttb-0.2.1.dist-info/METADATA
dttb-0.2.1.dist-info/RECORD
